{
    "_custom_": true, 
    "_ref_": 134278429, 
    "description": 895872560, 
    "fade_in_time": 0, 
    "fade_out_time": 0, 
    "icon": 100000, 
    "key": 134278429, 
    "kv": {}, 
    "max_dist": 1000, 
    "min_dist": 0, 
    "name": -735943640, 
    "sound_id": 1, 
    "sound_id_list": [
        {
            "probability": 100, 
            "sound_id": 122540, 
            "volume": 50
        }
    ], 
    "speed": 1, 
    "suffix": "", 
    "tags": {
        "__tuple__": true, 
        "items": []
    }, 
    "total_time": 0.417361111111, 
    "type": 1, 
    "uid": "134278429", 
    "volume": 50.0
}